virtughan/__init__.py
virtughan/engine.py
virtughan/extract.py
virtughan/tile.py
virtughan/utils.py
virtughan-1.0.1.dist-info/LICENSE
virtughan-1.0.1.dist-info/METADATA
virtughan-1.0.1.dist-info/WHEEL
virtughan-1.0.1.dist-info/RECORD
