Metadata-Version: 2.3
Name: virtughan
Version: 1.0.1
Summary: Virtual Computation Cube
License: GPL-3.0-or-later
Author: kshitijrajsharma
Author-email: skshitizraj@gmail.com
Requires-Python: >=3.10,<4.0
Classifier: License :: OSI Approved :: GNU General Public License v3 or later (GPLv3+)
Classifier: Programming Language :: Python :: 3
Classifier: Programming Language :: Python :: 3.10
Classifier: Programming Language :: Python :: 3.11
Classifier: Programming Language :: Python :: 3.12
Classifier: Programming Language :: Python :: 3.13
Requires-Dist: aiocache (>=0.12.3,<0.13.0)
Requires-Dist: fastapi (>=0.115.6,<0.116.0)
Requires-Dist: httpx (>=0.28.1,<0.29.0)
Requires-Dist: jinja2 (>=3.1.5,<4.0.0)
Requires-Dist: matplotlib (>=3.10.0,<4.0.0)
Requires-Dist: mercantile (>=1.2.1,<2.0.0)
Requires-Dist: mkdocstrings[python] (>=0.28.1,<0.29.0)
Requires-Dist: numpy (>=2.2.1,<3.0.0)
Requires-Dist: pillow (>=11.0.0,<12.0.0)
Requires-Dist: requests (>=2.32.3,<3.0.0)
Requires-Dist: rio-tiler (>=7.2.2,<8.0.0)
Requires-Dist: shapely (>=2.0.6,<3.0.0)
Requires-Dist: tqdm (>=4.67.1,<5.0.0)
Requires-Dist: uvicorn (>=0.34.0,<0.35.0)
